{
  "project_info": {
    "project_number": "178898204747",
    "project_id": "okuz-ai",
    "storage_bucket": "okuz-ai.firebasestorage.app"
  },
  "client": [
    {
      "client_info": {
        "mobilesdk_app_id": "1:178898204747:android:ac0c7a85824ee139fd75ce",
        "android_client_info": {
          "package_name": "com.okuz.ai"
        }
      },
      "oauth_client": [
        {
          "client_id": "178898204747-v4k80caph8u5ind13o8n6a696fivg7jc.apps.googleusercontent.com",
          "client_type": 1,
          "android_info": {
            "package_name": "com.okuz.ai",
            "certificate_hash": "059ff80983bf3f08a690ad51c4f652879cfb18a6"
          }
        },
        {
          "client_id": "178898204747-b11gusmt8did9jh8lk4i8h397096k6r5.apps.googleusercontent.com",
          "client_type": 3
        }
      ],
      "api_key": [
        {
          "current_key": "AIzaSyAnZb8ZCGTnojlvjr--cOiDDPXLO-5-yk8"
        }
      ],
      "services": {
        "appinvite_service": {
          "other_platform_oauth_client": [
            {
              "client_id": "178898204747-b11gusmt8did9jh8lk4i8h397096k6r5.apps.googleusercontent.com",
              "client_type": 3
            }
          ]
        }
      }
    }
  ],
  "configuration_version": "1"
}